LICENSE.txt
MANIFEST.in
README.rst
setup.cfg
setup.py
iiqtools/__init__.py
iiqtools/exceptions.py
iiqtools/iiqtools_gather_info.py
iiqtools/iiqtools_patch.py
iiqtools/iiqtools_tar_to_zip.py
iiqtools/iiqtools_version.py
iiqtools.egg-info/PKG-INFO
iiqtools.egg-info/SOURCES.txt
iiqtools.egg-info/dependency_links.txt
iiqtools.egg-info/top_level.txt
iiqtools/utils/__init__.py
iiqtools/utils/cli_parsers.py
iiqtools/utils/database.py
iiqtools/utils/generic.py
iiqtools/utils/logger.py
iiqtools/utils/shell.py
iiqtools/utils/versions.py
iiqtools_tests/__init__.py
iiqtools_tests/test_exceptions.py
iiqtools_tests/test_iiqtools_gather_info.py
iiqtools_tests/test_iiqtools_patch.py
iiqtools_tests/test_iiqtools_tar_to_zip.py
iiqtools_tests/test_iiqtools_version.py
iiqtools_tests/utils/__init__.py
iiqtools_tests/utils/test_cli_parsers.py
iiqtools_tests/utils/test_database.py
iiqtools_tests/utils/test_generic.py
iiqtools_tests/utils/test_logger.py
iiqtools_tests/utils/test_shell.py
iiqtools_tests/utils/test_versions.py
scripts/iiqtools_gather_info
scripts/iiqtools_patch
scripts/iiqtools_tar_to_zip
scripts/iiqtools_version