Metadata-Version: 1.1
Name: iiqtools
Version: 2.0.0
Summary: Scripts to help debug and support InsightIQ
Home-page: https://github.com/willnx/iiqtools
Author: Nicholas Willhite,
Author-email: willhite.nicholas@gmail.com
License: Copyright 2017 Dell EMC, Licensed under the Apache License, Version 2.0
